{"title":"Blog","markdown":{"yaml":{"title":"Blog"},"headingText":"Blog","containsRefs":false,"markdown":"\n\n\nWelcome to my blog! Here I share insights from my learning journey, technical discoveries, and thoughts on software development.\n\n## Recent Posts\n\n### Learning Journey Updates\n\n#### [My System Design Learning Path](/blog/system-design-learning-path)\n**Date**: March 2024  \n**Category**: System Design\n\nI've been diving deep into system design concepts and wanted to share my structured learning approach. From basic scalability patterns to complex distributed systems, here's how I'm building my knowledge systematically.\n\n#### [DSA Problem-Solving Techniques](/blog/dsa-problem-solving)\n**Date**: February 2024  \n**Category**: DSA\n\nAfter solving 100+ LeetCode problems, I've identified common patterns and techniques that make problem-solving more systematic. This post covers my approach to tackling different types of algorithmic challenges.\n\n#### [Technical Blog Analysis: Netflix's Chaos Engineering](/blog/netflix-chaos-engineering)\n**Date**: January 2024  \n**Category**: Technical Blogs\n\nA deep dive into Netflix's chaos engineering practices and how they ensure system resilience. I break down the key concepts and show how to apply these principles to your own systems.\n\n## Blog Categories\n\n### 🧮 **DSA & Algorithms**\n- Problem-solving techniques and strategies\n- Algorithm analysis and optimization\n- Interview preparation tips and experiences\n- Competitive programming insights\n\n### 🏗️ **System Design**\n- Architecture patterns and best practices\n- Scalability and performance optimization\n- Distributed systems concepts\n- Real-world system design case studies\n\n### 📝 **Technical Blog Breakdowns**\n- Analysis of engineering blog posts\n- Key insights from industry leaders\n- Practical applications of concepts\n- Learning resources and recommendations\n\n### 📚 **Book Reviews & Notes**\n- Detailed book summaries and takeaways\n- Reading progress and recommendations\n- Implementation of book concepts\n- Learning strategies and tips\n\n### 💻 **Programming & Development**\n- Language-specific tips and tricks\n- Best practices and code quality\n- Development tools and workflows\n- Project experiences and lessons learned\n\n### 🔧 **DevOps & Infrastructure**\n- Containerization and orchestration\n- Cloud platforms and services\n- CI/CD pipelines and automation\n- Monitoring and observability\n\n## Writing Style\n\n### **Educational Focus**\n- Clear explanations of complex concepts\n- Practical examples and code snippets\n- Step-by-step tutorials and guides\n- Real-world applications and case studies\n\n### **Personal Perspective**\n- My learning journey and experiences\n- Challenges faced and solutions found\n- Mistakes made and lessons learned\n- Growth and progress over time\n\n### **Community-Oriented**\n- Sharing knowledge with others\n- Encouraging discussion and feedback\n- Building connections with fellow developers\n- Contributing to the broader tech community\n\n## Upcoming Posts\n\n### **Planned Content**\n- [ ] \"Building a Scalable Web Application: Lessons Learned\"\n- [ ] \"My Kubernetes Learning Journey: From Docker to Orchestration\"\n- [ ] \"Technical Blog Analysis: Uber's Real-time Data Platform\"\n- [ ] \"Book Review: Designing Data-Intensive Applications\"\n- [ ] \"DSA Interview Preparation: My 3-Month Plan\"\n\n### **Series Ideas**\n- **\"System Design Deep Dive\"**: Multi-part series on scalable architecture\n- **\"DSA Problem Patterns\"**: Common algorithmic patterns and solutions\n- **\"Technical Blog Analysis\"**: Regular breakdowns of engineering articles\n- **\"Learning Path Guides\"**: Structured learning recommendations\n\n## Guest Posts & Collaboration\n\n### **Contributing**\nI welcome guest posts from other developers and learners. If you'd like to contribute:\n\n- **Topic Ideas**: Share your expertise and experiences\n- **Technical Tutorials**: Step-by-step guides and walkthroughs\n- **Case Studies**: Real-world project experiences\n- **Learning Journeys**: Your own path to mastering concepts\n\n### **Collaboration Opportunities**\n- **Joint Posts**: Co-author articles on complex topics\n- **Interview Series**: Q&A with experienced developers\n- **Study Groups**: Collaborative learning content\n- **Project Showcases**: Highlighting community projects\n\n## Blog Statistics\n\n### **Content Metrics**\n- **Total Posts**: 15+ articles\n- **Monthly Views**: Growing steadily\n- **Engagement**: Active discussions in comments\n- **Topics Covered**: DSA, System Design, Technical Blogs, Books\n\n### **Reader Engagement**\n- **Comments**: Thoughtful discussions on technical topics\n- **Social Shares**: Content shared across developer communities\n- **Feedback**: Valuable insights from readers\n- **Questions**: Technical questions and clarifications\n\n## Reading Recommendations\n\n### **For Beginners**\n- Start with the \"Learning Path Guides\" series\n- Focus on fundamental DSA concepts\n- Build a strong foundation before diving into advanced topics\n\n### **For Intermediate Developers**\n- Explore system design patterns and case studies\n- Practice with the provided code examples\n- Engage in discussions and share your experiences\n\n### **For Advanced Developers**\n- Contribute guest posts and share your expertise\n- Provide feedback and suggestions for improvement\n- Mentor others in their learning journey\n\n## Stay Connected\n\n### **Newsletter**\nSubscribe to get notified about new posts and learning updates:\n\n[Subscribe to Newsletter](#)\n\n### **Social Media**\n- **Twitter**: [@yourhandle](#) - Quick thoughts and updates\n- **LinkedIn**: [Your Profile](#) - Professional insights\n- **GitHub**: [Your Profile](#) - Code examples and projects\n\n### **RSS Feed**\nGet updates via RSS: [RSS Feed](blog.xml)\n\n## Blogging Goals\n\n### **2024 Objectives**\n- **Publish Frequency**: 2-3 posts per month\n- **Content Quality**: In-depth, well-researched articles\n- **Community Engagement**: Active discussions and feedback\n- **Skill Development**: Improve writing and communication\n\n### **Long-term Vision**\n- **Thought Leadership**: Establish expertise in key areas\n- **Community Building**: Create a learning-focused community\n- **Knowledge Sharing**: Help others in their learning journey\n- **Professional Growth**: Build a strong personal brand\n\n::: {.callout-tip}\n## Writing Tips for Developers\n- **Start with an outline**: Plan your post structure before writing\n- **Include code examples**: Show, don't just tell\n- **Use clear explanations**: Break down complex concepts\n- **Engage with readers**: Encourage comments and discussion\n- **Be consistent**: Regular posting builds audience\n:::\n\n::: {.callout-warning}\n## Common Blogging Mistakes\n- **Too much theory**: Balance with practical examples\n- **Poor formatting**: Use headers, lists, and code blocks\n- **No engagement**: Respond to comments and questions\n- **Inconsistent posting**: Maintain regular schedule\n:::\n\n","srcMarkdownNoYaml":"\n\n# Blog\n\nWelcome to my blog! Here I share insights from my learning journey, technical discoveries, and thoughts on software development.\n\n## Recent Posts\n\n### Learning Journey Updates\n\n#### [My System Design Learning Path](/blog/system-design-learning-path)\n**Date**: March 2024  \n**Category**: System Design\n\nI've been diving deep into system design concepts and wanted to share my structured learning approach. From basic scalability patterns to complex distributed systems, here's how I'm building my knowledge systematically.\n\n#### [DSA Problem-Solving Techniques](/blog/dsa-problem-solving)\n**Date**: February 2024  \n**Category**: DSA\n\nAfter solving 100+ LeetCode problems, I've identified common patterns and techniques that make problem-solving more systematic. This post covers my approach to tackling different types of algorithmic challenges.\n\n#### [Technical Blog Analysis: Netflix's Chaos Engineering](/blog/netflix-chaos-engineering)\n**Date**: January 2024  \n**Category**: Technical Blogs\n\nA deep dive into Netflix's chaos engineering practices and how they ensure system resilience. I break down the key concepts and show how to apply these principles to your own systems.\n\n## Blog Categories\n\n### 🧮 **DSA & Algorithms**\n- Problem-solving techniques and strategies\n- Algorithm analysis and optimization\n- Interview preparation tips and experiences\n- Competitive programming insights\n\n### 🏗️ **System Design**\n- Architecture patterns and best practices\n- Scalability and performance optimization\n- Distributed systems concepts\n- Real-world system design case studies\n\n### 📝 **Technical Blog Breakdowns**\n- Analysis of engineering blog posts\n- Key insights from industry leaders\n- Practical applications of concepts\n- Learning resources and recommendations\n\n### 📚 **Book Reviews & Notes**\n- Detailed book summaries and takeaways\n- Reading progress and recommendations\n- Implementation of book concepts\n- Learning strategies and tips\n\n### 💻 **Programming & Development**\n- Language-specific tips and tricks\n- Best practices and code quality\n- Development tools and workflows\n- Project experiences and lessons learned\n\n### 🔧 **DevOps & Infrastructure**\n- Containerization and orchestration\n- Cloud platforms and services\n- CI/CD pipelines and automation\n- Monitoring and observability\n\n## Writing Style\n\n### **Educational Focus**\n- Clear explanations of complex concepts\n- Practical examples and code snippets\n- Step-by-step tutorials and guides\n- Real-world applications and case studies\n\n### **Personal Perspective**\n- My learning journey and experiences\n- Challenges faced and solutions found\n- Mistakes made and lessons learned\n- Growth and progress over time\n\n### **Community-Oriented**\n- Sharing knowledge with others\n- Encouraging discussion and feedback\n- Building connections with fellow developers\n- Contributing to the broader tech community\n\n## Upcoming Posts\n\n### **Planned Content**\n- [ ] \"Building a Scalable Web Application: Lessons Learned\"\n- [ ] \"My Kubernetes Learning Journey: From Docker to Orchestration\"\n- [ ] \"Technical Blog Analysis: Uber's Real-time Data Platform\"\n- [ ] \"Book Review: Designing Data-Intensive Applications\"\n- [ ] \"DSA Interview Preparation: My 3-Month Plan\"\n\n### **Series Ideas**\n- **\"System Design Deep Dive\"**: Multi-part series on scalable architecture\n- **\"DSA Problem Patterns\"**: Common algorithmic patterns and solutions\n- **\"Technical Blog Analysis\"**: Regular breakdowns of engineering articles\n- **\"Learning Path Guides\"**: Structured learning recommendations\n\n## Guest Posts & Collaboration\n\n### **Contributing**\nI welcome guest posts from other developers and learners. If you'd like to contribute:\n\n- **Topic Ideas**: Share your expertise and experiences\n- **Technical Tutorials**: Step-by-step guides and walkthroughs\n- **Case Studies**: Real-world project experiences\n- **Learning Journeys**: Your own path to mastering concepts\n\n### **Collaboration Opportunities**\n- **Joint Posts**: Co-author articles on complex topics\n- **Interview Series**: Q&A with experienced developers\n- **Study Groups**: Collaborative learning content\n- **Project Showcases**: Highlighting community projects\n\n## Blog Statistics\n\n### **Content Metrics**\n- **Total Posts**: 15+ articles\n- **Monthly Views**: Growing steadily\n- **Engagement**: Active discussions in comments\n- **Topics Covered**: DSA, System Design, Technical Blogs, Books\n\n### **Reader Engagement**\n- **Comments**: Thoughtful discussions on technical topics\n- **Social Shares**: Content shared across developer communities\n- **Feedback**: Valuable insights from readers\n- **Questions**: Technical questions and clarifications\n\n## Reading Recommendations\n\n### **For Beginners**\n- Start with the \"Learning Path Guides\" series\n- Focus on fundamental DSA concepts\n- Build a strong foundation before diving into advanced topics\n\n### **For Intermediate Developers**\n- Explore system design patterns and case studies\n- Practice with the provided code examples\n- Engage in discussions and share your experiences\n\n### **For Advanced Developers**\n- Contribute guest posts and share your expertise\n- Provide feedback and suggestions for improvement\n- Mentor others in their learning journey\n\n## Stay Connected\n\n### **Newsletter**\nSubscribe to get notified about new posts and learning updates:\n\n[Subscribe to Newsletter](#)\n\n### **Social Media**\n- **Twitter**: [@yourhandle](#) - Quick thoughts and updates\n- **LinkedIn**: [Your Profile](#) - Professional insights\n- **GitHub**: [Your Profile](#) - Code examples and projects\n\n### **RSS Feed**\nGet updates via RSS: [RSS Feed](blog.xml)\n\n## Blogging Goals\n\n### **2024 Objectives**\n- **Publish Frequency**: 2-3 posts per month\n- **Content Quality**: In-depth, well-researched articles\n- **Community Engagement**: Active discussions and feedback\n- **Skill Development**: Improve writing and communication\n\n### **Long-term Vision**\n- **Thought Leadership**: Establish expertise in key areas\n- **Community Building**: Create a learning-focused community\n- **Knowledge Sharing**: Help others in their learning journey\n- **Professional Growth**: Build a strong personal brand\n\n::: {.callout-tip}\n## Writing Tips for Developers\n- **Start with an outline**: Plan your post structure before writing\n- **Include code examples**: Show, don't just tell\n- **Use clear explanations**: Break down complex concepts\n- **Engage with readers**: Encourage comments and discussion\n- **Be consistent**: Regular posting builds audience\n:::\n\n::: {.callout-warning}\n## Common Blogging Mistakes\n- **Too much theory**: Balance with practical examples\n- **Poor formatting**: Use headers, lists, and code blocks\n- **No engagement**: Respond to comments and questions\n- **Inconsistent posting**: Maintain regular schedule\n:::\n\n"},"formats":{"html":{"identifier":{"display-name":"HTML","target-format":"html","base-format":"html"},"execute":{"fig-width":7,"fig-height":5,"fig-format":"retina","fig-dpi":96,"df-print":"default","error":false,"eval":true,"cache":null,"freeze":false,"echo":true,"output":true,"warning":true,"include":true,"keep-md":false,"keep-ipynb":false,"ipynb":null,"enabled":null,"daemon":null,"daemon-restart":false,"debug":false,"ipynb-filters":[],"ipynb-shell-interactivity":null,"plotly-connected":true,"engine":"markdown"},"render":{"keep-tex":false,"keep-typ":false,"keep-source":false,"keep-hidden":false,"prefer-html":false,"output-divs":true,"output-ext":"html","fig-align":"default","fig-pos":null,"fig-env":null,"code-fold":"none","code-overflow":"scroll","code-link":false,"code-line-numbers":false,"code-tools":false,"tbl-colwidths":"auto","merge-includes":true,"inline-includes":false,"preserve-yaml":false,"latex-auto-mk":true,"latex-auto-install":true,"latex-clean":true,"latex-min-runs":1,"latex-max-runs":10,"latex-makeindex":"makeindex","latex-makeindex-opts":[],"latex-tlmgr-opts":[],"latex-input-paths":[],"latex-output-dir":null,"link-external-icon":false,"link-external-newwindow":false,"self-contained-math":false,"format-resources":[],"notebook-links":true},"pandoc":{"standalone":true,"wrap":"none","default-image-extension":"png","to":"html","css":["css/styles.css"],"toc":true,"html-math-method":"katex","include-after-body":["footer.html"],"filters":["abstract-section"],"output-file":"blog.html"},"language":{"toc-title-document":"Table of contents","toc-title-website":"On this page","related-formats-title":"Other Formats","related-notebooks-title":"Notebooks","source-notebooks-prefix":"Source","other-links-title":"Other Links","code-links-title":"Code Links","launch-dev-container-title":"Launch Dev Container","launch-binder-title":"Launch Binder","article-notebook-label":"Article Notebook","notebook-preview-download":"Download Notebook","notebook-preview-download-src":"Download Source","notebook-preview-back":"Back to Article","manuscript-meca-bundle":"MECA Bundle","section-title-abstract":"Abstract","section-title-appendices":"Appendices","section-title-footnotes":"Footnotes","section-title-references":"References","section-title-reuse":"Reuse","section-title-copyright":"Copyright","section-title-citation":"Citation","appendix-attribution-cite-as":"For attribution, please cite this work as:","appendix-attribution-bibtex":"BibTeX citation:","appendix-view-license":"View License","title-block-author-single":"Author","title-block-author-plural":"Authors","title-block-affiliation-single":"Affiliation","title-block-affiliation-plural":"Affiliations","title-block-published":"Published","title-block-modified":"Modified","title-block-keywords":"Keywords","callout-tip-title":"Tip","callout-note-title":"Note","callout-warning-title":"Warning","callout-important-title":"Important","callout-caution-title":"Caution","code-summary":"Code","code-tools-menu-caption":"Code","code-tools-show-all-code":"Show All Code","code-tools-hide-all-code":"Hide All Code","code-tools-view-source":"View Source","code-tools-source-code":"Source Code","tools-share":"Share","tools-download":"Download","code-line":"Line","code-lines":"Lines","copy-button-tooltip":"Copy to Clipboard","copy-button-tooltip-success":"Copied!","repo-action-links-edit":"Edit this page","repo-action-links-source":"View source","repo-action-links-issue":"Report an issue","back-to-top":"Back to top","search-no-results-text":"No results","search-matching-documents-text":"matching documents","search-copy-link-title":"Copy link to search","search-hide-matches-text":"Hide additional matches","search-more-match-text":"more match in this document","search-more-matches-text":"more matches in this document","search-clear-button-title":"Clear","search-text-placeholder":"","search-detached-cancel-button-title":"Cancel","search-submit-button-title":"Submit","search-label":"Search","toggle-section":"Toggle section","toggle-sidebar":"Toggle sidebar navigation","toggle-dark-mode":"Toggle dark mode","toggle-reader-mode":"Toggle reader mode","toggle-navigation":"Toggle navigation","crossref-fig-title":"Figure","crossref-tbl-title":"Table","crossref-lst-title":"Listing","crossref-thm-title":"Theorem","crossref-lem-title":"Lemma","crossref-cor-title":"Corollary","crossref-prp-title":"Proposition","crossref-cnj-title":"Conjecture","crossref-def-title":"Definition","crossref-exm-title":"Example","crossref-exr-title":"Exercise","crossref-ch-prefix":"Chapter","crossref-apx-prefix":"Appendix","crossref-sec-prefix":"Section","crossref-eq-prefix":"Equation","crossref-lof-title":"List of Figures","crossref-lot-title":"List of Tables","crossref-lol-title":"List of Listings","environment-proof-title":"Proof","environment-remark-title":"Remark","environment-solution-title":"Solution","listing-page-order-by":"Order By","listing-page-order-by-default":"Default","listing-page-order-by-date-asc":"Oldest","listing-page-order-by-date-desc":"Newest","listing-page-order-by-number-desc":"High to Low","listing-page-order-by-number-asc":"Low to High","listing-page-field-date":"Date","listing-page-field-title":"Title","listing-page-field-description":"Description","listing-page-field-author":"Author","listing-page-field-filename":"File Name","listing-page-field-filemodified":"Modified","listing-page-field-subtitle":"Subtitle","listing-page-field-readingtime":"Reading Time","listing-page-field-wordcount":"Word Count","listing-page-field-categories":"Categories","listing-page-minutes-compact":"{0} min","listing-page-category-all":"All","listing-page-no-matches":"No matching items","listing-page-words":"{0} words","listing-page-filter":"Filter","draft":"Draft"},"metadata":{"lang":"en","fig-responsive":true,"quarto-version":"1.7.32","theme":["simplex","custom.scss"],"js":"scripts.js","smooth-scroll":true,"anchor-sections":true,"page-layout":"full","title":"Blog"},"extensions":{"book":{"multiFile":true}}}},"projectFormats":["html"]}